objerve/__init__.py
objerve/color.py
objerve/objerve.py
objerve-0.2.0.dist-info/LICENSE
objerve-0.2.0.dist-info/METADATA
objerve-0.2.0.dist-info/WHEEL
objerve-0.2.0.dist-info/top_level.txt
objerve-0.2.0.dist-info/RECORD
