Metadata-Version: 2.1
Name: objerve
Version: 0.2.0
Summary: Tiny observer for the attributes of Python objects.
Home-page: https://github.com/furkanonder/objerve
Author: Furkan Onder
Author-email: furkanonder@protonmail.com
License: MIT
Keywords: monitoring,hook,observer
Classifier: Development Status :: 2 - Pre-Alpha
Classifier: License :: OSI Approved :: MIT License
Classifier: Intended Audience :: End Users/Desktop
Classifier: Programming Language :: Python :: 3
Classifier: Programming Language :: Python :: 3 :: Only
Classifier: Topic :: Software Development :: Libraries :: Python Modules
Classifier: Topic :: Utilities
Classifier: Operating System :: POSIX :: Linux
Classifier: Operating System :: Unix
Classifier: Operating System :: Microsoft :: Windows
Requires-Python: >=3.0
License-File: LICENSE
